colormaps/__init__.py
colormaps/cet_colormap.py
colormaps/hsv256_colormap.py
colormaps/landscape256_colormap.py
colormaps/make_colormap.py
colormaps/metallic256_colormap.py
colormaps/mymap_colormap.py
colormaps/pastels256_colormap.py
colormaps/tropical_colormap.py
colormaps/twilight256_colormap.py
colormaps/twilights512_colormap.py
pymandel/__init__.py
pymandel/__main__.py
pymandel/_version.py
pymandel/about_dialog.py
pymandel/app.py
pymandel/fractal_frame.py
pymandel/howto_dialog.py
pymandel/mandelbrot.py
pymandel/mandelcli.py
pymandel/menu_bar.py
pymandel/settings_frame.py
pymandel/status_frame.py
pymandel/strings.py
pymandel/stringsDE.py
pymandel/stringsEN.py
pymandel/stringsES.py
pymandel/stringsFR.py
pymandel/resources/pymandel.ico
pymandel/resources/pymandel.png
pymandel/resources/thumbnail.gif
pymandel-1.0.13.dist-info/LICENSE
pymandel-1.0.13.dist-info/METADATA
pymandel-1.0.13.dist-info/WHEEL
pymandel-1.0.13.dist-info/entry_points.txt
pymandel-1.0.13.dist-info/top_level.txt
pymandel-1.0.13.dist-info/RECORD
