Metadata-Version: 2.1
Name: pymandel
Version: 1.0.13
Summary: Fractal generation GUI application
Author-email: semuadmin <semuadmin@semuconsulting.com>
Maintainer-email: semuadmin <semuadmin@semuconsulting.com>
License: GNU GENERAL PUBLIC LICENSE
Project-URL: homepage, https://github.com/semuconsulting/pymandel
Project-URL: documentation, https://www.semuconsulting.com/pymandel/
Project-URL: repository, https://github.com/semuconsulting/pymandel
Project-URL: changelog, https://github.com/semuconsulting/pymandel/blob/master/RELEASE_NOTES.md
Keywords: PyMandel,fractal,Mandelbrot,Julia,Burning Ship,Tricorn,numba
Classifier: Operating System :: OS Independent
Classifier: Development Status :: 5 - Production/Stable
Classifier: Environment :: MacOS X
Classifier: Environment :: Win32 (MS Windows)
Classifier: Environment :: X11 Applications
Classifier: Environment :: Console
Classifier: Intended Audience :: End Users/Desktop
Classifier: Programming Language :: Python :: 3
Classifier: Programming Language :: Python :: 3.8
Classifier: Programming Language :: Python :: 3.9
Classifier: Programming Language :: Python :: 3.10
Classifier: Programming Language :: Python :: 3.11
Classifier: Programming Language :: Python :: 3.12
Classifier: License :: OSI Approved :: GNU General Public License v3 (GPLv3)
Classifier: Topic :: Multimedia :: Graphics
Classifier: Topic :: Scientific/Engineering :: Mathematics
Classifier: Topic :: Education
Classifier: Topic :: Utilities
Requires-Python: >=3.8
License-File: LICENSE
Requires-Dist: numba >=0.58.0
Requires-Dist: numpy >=1.21.6
Requires-Dist: Pillow >=9.3.0
Provides-Extra: deploy
Requires-Dist: build ; extra == 'deploy'
Requires-Dist: pip ; extra == 'deploy'
Requires-Dist: setuptools >=66.0 ; extra == 'deploy'
Requires-Dist: wheel ; extra == 'deploy'
Provides-Extra: test
Requires-Dist: bandit ; extra == 'test'
Requires-Dist: black ; extra == 'test'
Requires-Dist: pylint ; extra == 'test'
Requires-Dist: pytest ; extra == 'test'
Requires-Dist: pytest-cov ; extra == 'test'
Requires-Dist: Sphinx ; extra == 'test'
Requires-Dist: sphinx-rtd-theme ; extra == 'test'
